README.md
setup.py
latex_generator/__init__.py
latex_generator/generator.py
latex_generator_itmo_yuzik.egg-info/PKG-INFO
latex_generator_itmo_yuzik.egg-info/SOURCES.txt
latex_generator_itmo_yuzik.egg-info/dependency_links.txt
latex_generator_itmo_yuzik.egg-info/top_level.txt