Metadata-Version: 2.1
Name: latex-generator-itmo-yuzik
Version: 0.1.0
Summary: Simple LaTeX document generator with image inclusion.
Home-page: https://github.com/yuzik/Advanced-Python-ITMO/HW_2
Author: Joseph Ya
Author-email: yuzik.74@gmail.com
Classifier: Programming Language :: Python :: 3
Classifier: License :: OSI Approved :: MIT License
